valer.storage-1.0.2rc11-nspkg.pth
senaite/storage/__init__.py
senaite/storage/api.py
senaite/storage/catalog.py
senaite/storage/configure.zcml
senaite/storage/interfaces.py
senaite/storage/setuphandlers.py
senaite/storage/version.txt
senaite/storage/browser/__init__.py
senaite/storage/browser/analysisrequests.py
senaite/storage/browser/configure.zcml
senaite/storage/browser/containers.py
senaite/storage/browser/samples.py
senaite/storage/browser/storagelisting.py
senaite/storage/browser/storagerootfolder.py
senaite/storage/browser/store_container.py
senaite/storage/browser/store_samples.py
senaite/storage/browser/templates/store_container.pt
senaite/storage/browser/templates/store_samples.pt
senaite/storage/browser/viewlets/__init__.py
senaite/storage/browser/viewlets/configure.zcml
senaite/storage/browser/viewlets/sample_container.py
senaite/storage/browser/viewlets/templates/sample_container_viewlet.pt
senaite/storage/browser/workflow/__init__.py
senaite/storage/browser/workflow/analysisrequest.py
senaite/storage/browser/workflow/configure.zcml
senaite/storage/browser/workflow/storagecontainer.py
senaite/storage/content/__init__.py
senaite/storage/content/storagecontainer.py
senaite/storage/content/storagefacility.py
senaite/storage/content/storagelayoutcontainer.py
senaite/storage/content/storagerootfolder.py
senaite/storage/content/storagesamplescontainer.py
senaite/storage/locales/cs/LC_MESSAGES/senaite.storage.po
senaite/storage/locales/de/LC_MESSAGES/senaite.storage.po
senaite/storage/locales/en/LC_MESSAGES/senaite.storage.po
senaite/storage/locales/es/LC_MESSAGES/senaite.storage.po
senaite/storage/monkeys/__init__.py
senaite/storage/monkeys/configure.zcml
senaite/storage/monkeys/content/__init__.py
senaite/storage/monkeys/content/analysisrequest.py
senaite/storage/profiles/default/browserlayer.xml
senaite/storage/profiles/default/controlpanel.xml
senaite/storage/profiles/default/cssregistry.xml
valer.storage-1.0.2rc11.dist-info/DESCRIPTION.rst
valer.storage-1.0.2rc11.dist-info/METADATA
valer.storage-1.0.2rc11.dist-info/RECORD
valer.storage-1.0.2rc11.dist-info/WHEEL
valer.storage-1.0.2rc11.dist-info/entry_points.txt
valer.storage-1.0.2rc11.dist-info/metadata.json
valer.storage-1.0.2rc11.dist-info/namespace_packages.txt
valer.storage-1.0.2rc11.dist-info/top_level.txt
